Metadata-Version: 2.1
Name: graphub
Version: 0.0.1b0
Summary: Simple GraphQL client for Python
Home-page: https://github.com/srinivasreddy/graphub
Author: Srinivas Reddy Thatiparthy
Author-email: sr.thatiparthy+python@gmail.com
License: MIT
Platform: UNKNOWN
